{
  "Routes": [
    {
      "DownstreamPathTemplate": "/management/clients/{everything}",
      "DownstreamScheme": "https",
      "DownstreamHostAndPorts": [
        {
          "Host": "localhost",
          "Port": 60000
        }
      ],
      "UpstreamPathTemplate": "/applications/{everything}",
      "UpstreamHttpMethod": [ "POST", "GET" ],
      "DelegatingHandlers": [
        "ManageClientClientCredentialsHandler"
      ],
      "AuthenticationOptions": {
        "AuthenticationProviderKey": "Authenticated",
        "AllowedScopes": []
      }
    },
    {
      "DownstreamPathTemplate": "/metadata/{everything}",
      "DownstreamScheme": "https",
      "DownstreamHostAndPorts": [
        {
          "Host": "localhost",
          "Port": 60000
        }
      ],
      "UpstreamPathTemplate": "/metadata/{everything}",
      "UpstreamHttpMethod": [ "POST", "GET" ]
    }
  ],
  "ClientId": "gatewayClient",
  "ClientSecret": "gatewayClientPassword",
  "OAuthBaseUrl": "https://localhost:60000"
}